LICENSE.txt
MANIFEST.in
README.md
setup.py
colabcam/__init__.py
colabcam.egg-info/PKG-INFO
colabcam.egg-info/SOURCES.txt
colabcam.egg-info/dependency_links.txt
colabcam.egg-info/requires.txt
colabcam.egg-info/top_level.txt