Metadata-Version: 2.1
Name: colabcam
Version: 1.0.1
Summary: Process image from webcam in colab
Home-page: https://pypi.org/project/colabcam
Author: KuoYuan Li
Author-email: funny4875@gmail.com
License: UNKNOWN
Keywords: colab,webcam,javascript,take_photo,take_img,record_video_timed
Platform: UNKNOWN
Classifier: License :: OSI Approved :: MIT License
Classifier: Programming Language :: Python :: 3
